{"count_ships": 2710, "count_logs": 299328, "items_held": {"1": 9147149, "2": 7038218, "4": 423335, "5": 1293795, "6": 740879, "51": 8900, "53": 8677, "55": 9329, "56": 8873, "100": 3355, "101": 1248, "102": 44, "103": 2041, "104": 4749, "105": 93367, "106": 2955, "107": 753, "108": 3046, "109": 900, "110": 620, "111": 602, "112": 2379, "113": 752, "114": 2991, "115": 4935, "116": 4858, "117": 8, "120": 4897, "122": 897, "150": 319727, "151": 344418, "152": 921062, "153": 980819, "154": 1180813, "155": 317077, "156": 1129024, "157": 293677, "159": 340, "160": 169, "215": 688, "216": 2690, "217": 1620, "218": 2752, "219": 5134, "220": 52249, "221": 65832, "222": 2606, "223": 7600, "224": 1938, "226": 164269, "227": 4908, "228": 16645, "229": 17011, "230": 18415, "231": 5402, "232": 467087, "233": 12020, "234": 483143, "235": 94430, "236": 75954, "237": 126597, "239": 98082, "240": 48553, "241": 888, "242": 43989, "243": 5781, "245": 12421, "246": 94, "247": 2329, "248": 19271, "249": 5146, "250": 3629, "251": 735, "252": 258204, "253": 1348, "300": 4, "301": 2, "302": 2, "303": 2, "304": 2, "305": 1, "306": 4, "307": 11, "308": 60, "310": 1, "313": 14, "314": 14, "315": 1, "316": 1, "317": 14, "318": 2, "319": 1, "320": 1, "321": 6, "322": 6, "100000": 2710}, "items_moved": {"1": 817162, "2": 447422, "4": 7859, "5": 61997, "6": 68789, "51": 90, "53": 98, "55": 97, "56": 101, "100": 128, "101": 30, "103": 90, "104": 98, "105": 2381, "106": 1322, "107": 71, "108": 99, "109": 32, "110": 16, "111": 23, "112": 89, "113": 31, "114": 161, "115": 39, "116": 46, "120": 456, "122": 127, "150": 41631, "151": 51430, "152": 69778, "153": 79257, "154": 59876, "155": 11483, "156": 64863, "215": 9, "217": 64, "218": 20, "219": 188, "220": 2069, "221": 2565, "223": 268, "224": 12, "226": 6984, "228": 553, "229": 625, "230": 687, "232": 23878, "233": 36, "234": 13292, "235": 1697, "236": 1888, "237": 2386, "239": 12186, "240": 1186, "241": 15, "242": 1628, "243": 168, "245": 337, "248": 440, "249": 146, "250": 77, "251": 6, "252": 8882, "253": 39}, "items_new": [{"zone": "Finch", "src": "bot - yellow rusher", "item": 151, "total": 353846, "grabbed": 288010}, {"zone": "Hummingbird", "src": "bot - orange fool", "item": 150, "total": 279513, "grabbed": 251369}, {"zone": "Hummingbird", "src": "block - iron mine", "item": 1, "total": 260112, "grabbed": 251199}, {"zone": "Finch", "src": "bot - red sentry", "item": 153, "total": 172414, "grabbed": 148935}, {"zone": "Finch", "src": "block - iron mine", "item": 1, "total": 98344, "grabbed": 92576}, {"zone": "Sparrow", "src": "bot - blue melee", "item": 156, "total": 94542, "grabbed": 70053}, {"zone": "Sparrow", "src": "bot - red hunter", "item": 1, "total": 94248, "grabbed": 79679}, {"zone": "Sparrow", "src": "bot - red hunter", "item": 2, "total": 94176, "grabbed": 79411}, {"zone": "Sparrow", "src": "bot - blue melee", "item": 154, "total": 92761, "grabbed": 68033}, {"zone": "Sparrow", "src": "bot - blue melee", "item": 152, "total": 90744, "grabbed": 65577}, {"zone": "Finch", "src": "bot - yellow rusher", "item": 2, "total": 83860, "grabbed": 68726}, {"zone": "Finch", "src": "bot - red sentry", "item": 2, "total": 62147, "grabbed": 55096}, {"zone": "Sparrow", "src": "block - iron mine", "item": 1, "total": 22489, "grabbed": 18293}, {"zone": "Canary", "src": "block - flux node", "item": 5, "total": 11936, "grabbed": 11776}, {"zone": "Finch", "src": "bot - red sentry", "item": 6, "total": 11456, "grabbed": 7673}, {"zone": "The Pits", "src": "block - flux node", "item": 5, "total": 6160, "grabbed": 6096}, {"zone": "Sparrow", "src": "bot - green roamer", "item": 234, "total": 6080, "grabbed": 5312}, {"zone": "The Pits", "src": "giant rubber ball", "item": 4, "total": 3872, "grabbed": 3840}, {"zone": "Finch", "src": "block - flux mine", "item": 5, "total": 2480, "grabbed": 2336}, {"zone": "Hummingbird", "src": "block - flux mine", "item": 5, "total": 2208, "grabbed": 2092}, {"zone": "Hummingbird", "src": "bot - orange fool", "item": 226, "total": 1789, "grabbed": 1750}, {"zone": "Sparrow", "src": "block - flux mine", "item": 5, "total": 1444, "grabbed": 1304}, {"zone": "Finch", "src": "bot - yellow rusher", "item": 226, "total": 879, "grabbed": 758}, {"zone": "Canary", "src": "block - treasure diamond", "item": 226, "total": 757, "grabbed": 701}, {"zone": "Vulture", "src": "bot - zombie tank", "item": 1, "total": 304, "grabbed": 304}, {"zone": "The Pits", "src": "block - treasure diamond", "item": 226, "total": 289, "grabbed": 260}, {"zone": "Canary", "src": "block - treasure diamond", "item": 229, "total": 142, "grabbed": 86}, {"zone": "Canary", "src": "block - treasure diamond", "item": 228, "total": 138, "grabbed": 79}, {"zone": "Sparrow", "src": "bot - green roamer", "item": 120, "total": 134, "grabbed": 120}, {"zone": "Sparrow", "src": "bot - green roamer", "item": 252, "total": 130, "grabbed": 125}, {"zone": "Finch", "src": "bot - yellow rusher", "item": 229, "total": 105, "grabbed": 80}, {"zone": "Finch", "src": "bot - yellow rusher", "item": 228, "total": 71, "grabbed": 59}, {"zone": "Sparrow", "src": "bot - green roamer", "item": 242, "total": 66, "grabbed": 63}, {"zone": "Finch", "src": "bot - red sentry", "item": 108, "total": 64, "grabbed": 49}, {"zone": "Vulture", "src": "bot - zombie", "item": 226, "total": 61, "grabbed": 54}, {"zone": "The Pits", "src": "block - treasure diamond", "item": 229, "total": 57, "grabbed": 36}, {"zone": "Sparrow", "src": "bot - green roamer", "item": 243, "total": 54, "grabbed": 54}, {"zone": "Sparrow", "src": "bot - green roamer", "item": 53, "total": 53, "grabbed": 52}, {"zone": "Sparrow", "src": "bot - green roamer", "item": 55, "total": 50, "grabbed": 48}, {"zone": "Sparrow", "src": "bot - green roamer", "item": 56, "total": 46, "grabbed": 37}, {"zone": "Sparrow", "src": "bot - green roamer", "item": 51, "total": 44, "grabbed": 39}, {"zone": "The Pits", "src": "block - treasure diamond", "item": 228, "total": 44, "grabbed": 35}, {"zone": "Sparrow", "src": "bot - red hunter", "item": 104, "total": 28, "grabbed": 21}, {"zone": "Finch", "src": "bot - red sentry", "item": 115, "total": 24, "grabbed": 21}, {"zone": "Sparrow", "src": "bot - green roamer", "item": 122, "total": 22, "grabbed": 21}, {"zone": "Finch", "src": "bot - red sentry", "item": 116, "total": 22, "grabbed": 18}, {"zone": "Sparrow", "src": "bot - blue melee", "item": 111, "total": 15, "grabbed": 10}, {"zone": "Sparrow", "src": "bot - blue melee", "item": 114, "total": 13, "grabbed": 10}, {"zone": "Sparrow", "src": "bot - blue melee", "item": 113, "total": 11, "grabbed": 9}, {"zone": "Sparrow", "src": "bot - blue melee", "item": 112, "total": 10, "grabbed": 8}, {"zone": "Sparrow", "src": "bot - blue melee", "item": 110, "total": 9, "grabbed": 8}, {"zone": "Sparrow", "src": "bot - blue melee", "item": 109, "total": 8, "grabbed": 7}, {"zone": "Vulture", "src": "bot - zombie tank", "item": 5, "total": 8, "grabbed": 8}, {"zone": "Vulture", "src": "bot - zombie tank", "item": 226, "total": 8, "grabbed": 8}]}